superscript/__init__.py
superscript/__main__.py
superscript/main.py
superscript-0.1.1.dist-info/entry_points.txt
superscript-0.1.1.dist-info/WHEEL
superscript-0.1.1.dist-info/METADATA
superscript-0.1.1.dist-info/RECORD
