Metadata-Version: 2.1
Name: superscript
Version: 0.1.1
Summary: Dynamical software components manager.
Author: toxicphreAK
Author-email: pentesting.laboratories@gmail.com
Requires-Python: >=3.8,<4.0
Classifier: Programming Language :: Python :: 3
Classifier: Programming Language :: Python :: 3.10
Classifier: Programming Language :: Python :: 3.8
Classifier: Programming Language :: Python :: 3.9
Requires-Dist: GitPython (>=3.1.7,<4.0.0)
Requires-Dist: pyyaml (>=5.3.1,<6.0.0)
Requires-Dist: requests (>=2.24.0,<3.0.0)
Requires-Dist: rich (>=4.2.2,<5.0.0)
Requires-Dist: typer[all] (>=0.3.1,<0.4.0)
